LICENSE
MANIFEST.in
README.md
droptables.py
master-test.sh
requirements.txt
setup.py
geminicassandra/GeminiQuery.py
geminicassandra/__init__.py
geminicassandra/anno_info.py
geminicassandra/annotations.py
geminicassandra/compression.py
geminicassandra/config.py
geminicassandra/database_cassandra.py
geminicassandra/dgidb.py
geminicassandra/func_impact.py
geminicassandra/gemini_amend.py
geminicassandra/gemini_annotate.py
geminicassandra/gemini_browser.py
geminicassandra/gemini_constants.py
geminicassandra/gemini_dbinfo.py
geminicassandra/gemini_load.py
geminicassandra/gemini_load_chunk.py
geminicassandra/gemini_main.py
geminicassandra/gemini_plot.py
geminicassandra/gemini_query.py
geminicassandra/gemini_region.py
geminicassandra/gemini_stats.py
geminicassandra/gemini_subjects.py
geminicassandra/gemini_update.py
geminicassandra/gemini_utils.py
geminicassandra/gene_table.py
geminicassandra/infotag.py
geminicassandra/install-data.py
geminicassandra/ped.py
geminicassandra/popgen.py
geminicassandra/query_expressions.py
geminicassandra/severe_impact.py
geminicassandra/snpEff.py
geminicassandra/sql.py
geminicassandra/sql_extended.py
geminicassandra/sql_utils.py
geminicassandra/stats.py
geminicassandra/structural_variants.py
geminicassandra/table_schemes.py
geminicassandra/vep.py
geminicassandra/version.py
geminicassandra.egg-info/PKG-INFO
geminicassandra.egg-info/SOURCES.txt
geminicassandra.egg-info/dependency_links.txt
geminicassandra.egg-info/not-zip-safe
geminicassandra.egg-info/requires.txt
geminicassandra.egg-info/top_level.txt
geminicassandra/data/__init__.py
geminicassandra/scripts/__init__.py
geminicassandra/scripts/gemini_install.py
geminicassandra/scripts/geminicassandra
test/ALL.wgs.phase1_release_v3.20101123.snps_indels_sv.sites.snippet.snpEff.vcf
test/ALL.wgs.phase1_release_v3.20101123.snps_indels_sv.sites.snippet.vcf
test/cassandra-test-query.sh
test/cassandra-test-setup.sh
test/data-setup.sh
test/exp
test/obs
test/querylog
test/test-clinvar.sh
test/test-columns.sh
test/test-exac.sh
test/test-genome.sh
test/test-genotypes.sh
test/test-load.sh
test/test-query-multicore.sh
test/test-query.sh
test/test-wildcards-multicore.sh
test/test-wildcards.sh
test/test.auto_dom.no_parents.2.ped
